flex_object/__init__.py
flex_object/flex_object.py
flex_object-1.0.0.dist-info/LICENSE
flex_object-1.0.0.dist-info/METADATA
flex_object-1.0.0.dist-info/WHEEL
flex_object-1.0.0.dist-info/top_level.txt
flex_object-1.0.0.dist-info/RECORD
