Metadata-Version: 2.1
Name: flex-object
Version: 1.0.0
Summary: FlexObject is a Python class that provides dynamic attribute management, runtime attribute addition/removal, JSON serialization, and JSON file/str reading.
Home-page: https://github.com/davidsantana06/flex-object
Author: David Santana
Author-email: davidsantana06@hotmail.com
License: UNKNOWN
Project-URL: Bug Tracker, https://github.com/davidsantana06/flex-object/issues
Platform: UNKNOWN
Classifier: Programming Language :: Python :: 3
Classifier: License :: OSI Approved :: MIT License
Classifier: Operating System :: OS Independent
Requires-Python: >=3.6
License-File: LICENSE
